cdcdeaths.py
cdcdeaths-0.0.2.dist-info/METADATA
cdcdeaths-0.0.2.dist-info/WHEEL
cdcdeaths-0.0.2.dist-info/entry_points.txt
cdcdeaths-0.0.2.dist-info/top_level.txt
cdcdeaths-0.0.2.dist-info/RECORD
