Metadata-Version: 2.1
Name: cdcdeaths
Version: 0.0.2
Summary: A package for visualizing the number of deaths by age groups
Home-page: https://github.com/y-takefuji/cdcdeaths
Author: yoshiyasu takefuji
Author-email: takefuji@keio.jp
License: UNKNOWN
Project-URL: Bug Tracker, https://github.com/y-takefuji/cdcdeaths
Platform: UNKNOWN
Classifier: Programming Language :: Python :: 3
Classifier: License :: OSI Approved :: MIT License
Classifier: Operating System :: OS Independent
Requires-Python: >=3.8
